{"number": 2739, "ref": "2022-04-simplify-GetSubstitution", "login": "gibson042", "head": "02888a160c8c3e39ad16484a6066bb1d7a9cbc34", "base": "4f72173f519821597b505a79c0f3a4451fb927e0", "title": "Editorial: Simplify GetSubstitution", "created_at": "2022-04-14T16:14:09Z", "updated_at": "2022-04-14T16:14:09Z", "revs": [{"hash": "02888a160c8c3e39ad16484a6066bb1d7a9cbc34", "parents": "189181374258343a0f9061e63d0e09444518685f", "author": "Richard Gibson", "date": "2022-04-14T12:08:45-04:00", "adate": "2022-04-14T12:08:45-04:00", "subject": "Editorial: Make an alias name more clear"}, {"hash": "189181374258343a0f9061e63d0e09444518685f", "parents": "9403cc341ac47e131ed83a2ffeceb093d58eb0b5", "author": "Richard Gibson", "date": "2022-04-14T12:04:13-04:00", "adate": "2022-04-14T12:04:13-04:00", "subject": "Editorial: Combine out-of-bounds index branches in GetSubstitution"}, {"hash": "9403cc341ac47e131ed83a2ffeceb093d58eb0b5", "parents": "4f72173f519821597b505a79c0f3a4451fb927e0", "author": "Richard Gibson", "date": "2022-04-14T11:57:16-04:00", "adate": "2022-04-14T11:57:16-04:00", "subject": "Editorial: Remove an unnecessary \"for each\" step from GetSubstitution"}]}