{"number": 2681, "ref": "CES_closure", "login": "jmdyck", "head": "78d49b5e9bac02d146652af04a5310086406fa1c", "base": "cbd5493ae4d0ad72e4e658e47764638c025c2edf", "title": "Editorial: Use Abstract Closure to set the code eval state", "created_at": "2022-03-03T04:23:30Z", "updated_at": "2022-03-03T04:23:30Z", "revs": [{"hash": "78d49b5e9bac02d146652af04a5310086406fa1c", "parents": "41c11feb47b815e87915ef7400b6203e90904bb9", "author": "Michael Dyck", "date": "2022-03-02T23:12:44-05:00", "adate": "2022-03-02T13:05:13-05:00", "subject": "fixup: Reduce the number of captured aliases"}, {"hash": "41c11feb47b815e87915ef7400b6203e90904bb9", "parents": "cbd5493ae4d0ad72e4e658e47764638c025c2edf", "author": "Michael Dyck", "date": "2022-03-02T23:12:44-05:00", "adate": "2022-03-01T21:18:32-05:00", "subject": "Editorial: Use Abstract Closure to set the code eval state"}]}