{"number": 2745, "ref": "unknown", "login": "jmdyck", "head": "c24817cdf483151e34ab48954bc908b828515f37", "base": "dceb9e45fa04ff37a213095e97a28da81bf213ec", "title": "Editorial: Eliminate \"unknown\" as a parameter type", "created_at": "2022-04-18T18:39:42Z", "updated_at": "2022-08-30T20:18:11Z", "revs": [{"hash": "c24817cdf483151e34ab48954bc908b828515f37", "parents": "af2ac03b40687e1603d2438e9150afbb15097e05", "author": "Michael Dyck", "date": "2022-08-30T15:59:59-04:00", "adate": "2022-08-30T15:59:59-04:00", "subject": "fixup: Narrow the type of `_call_` in IsInTailPosition and HasCallInTailPosition"}, {"hash": "af2ac03b40687e1603d2438e9150afbb15097e05", "parents": "5e481a0fc45726f4b0458f4043a304be95e94369", "author": "Michael Dyck", "date": "2022-08-30T14:57:56-04:00", "adate": "2022-08-30T14:57:56-04:00", "subject": "fixup: NamedEvaluation's _name_ must also accept Symbol and Private Name"}, {"hash": "5e481a0fc45726f4b0458f4043a304be95e94369", "parents": "a8582b70b74b3052142e3ab5c2a02b691c03e3b4", "author": "Michael Dyck", "date": "2022-08-30T10:15:42-04:00", "adate": "2022-08-30T10:15:42-04:00", "subject": "fixup: ~[empty]~ to ~empty~ after PR #2862"}, {"hash": "a8582b70b74b3052142e3ab5c2a02b691c03e3b4", "parents": "8cb91102d7e61ad6737ac53d5dea13102554236c", "author": "Michael Dyck", "date": "2022-08-30T10:07:43-04:00", "adate": "2022-04-16T16:29:16-04:00", "subject": "31x \"unknown\" -> miscellaneous"}, {"hash": "8cb91102d7e61ad6737ac53d5dea13102554236c", "parents": "8c752b286f85736f61a8c0c127008c84d02e4d5f", "author": "Michael Dyck", "date": "2022-08-30T10:07:43-04:00", "adate": "2022-04-16T16:26:05-04:00", "subject": "3x \"unknown\" -> \"a property key\""}, {"hash": "8c752b286f85736f61a8c0c127008c84d02e4d5f", "parents": "2e559cba6b9736c51a9ea4d7dc38361205ccfdbe", "author": "Michael Dyck", "date": "2022-08-30T10:07:43-04:00", "adate": "2022-04-16T16:24:46-04:00", "subject": "5x \"unknown\" -> \"a List of ECMAScript language values\""}, {"hash": "2e559cba6b9736c51a9ea4d7dc38361205ccfdbe", "parents": "fedc97e1c017a36aee5629313a095eccd61e311a", "author": "Michael Dyck", "date": "2022-08-30T10:07:43-04:00", "adate": "2022-04-16T16:23:46-04:00", "subject": "5x \"unknown\" -> \"a Realm Record\""}, {"hash": "fedc97e1c017a36aee5629313a095eccd61e311a", "parents": "74148b80a1f91cd20602813a6909423bb8190701", "author": "Michael Dyck", "date": "2022-08-30T10:07:43-04:00", "adate": "2022-04-16T16:18:30-04:00", "subject": "5x \"unknown\" -> \"a constructor\""}, {"hash": "74148b80a1f91cd20602813a6909423bb8190701", "parents": "3b91299b626695fba6f3b2262bbf7f730d2024fe", "author": "Michael Dyck", "date": "2022-08-30T10:07:43-04:00", "adate": "2022-04-16T16:17:14-04:00", "subject": "6x \"unknown\" -> \"a Boolean\""}, {"hash": "3b91299b626695fba6f3b2262bbf7f730d2024fe", "parents": "28c8b44d67afd13a484bf461eefec6bcb18c30d4", "author": "Michael Dyck", "date": "2022-08-30T10:07:42-04:00", "adate": "2022-04-16T16:15:41-04:00", "subject": "6x \"unknown\" -> \"a PrivateEnvironment Record or *null*\""}, {"hash": "28c8b44d67afd13a484bf461eefec6bcb18c30d4", "parents": "57d6f4916a8008399a34e79487d3800087bbeb58", "author": "Michael Dyck", "date": "2022-08-30T10:07:42-04:00", "adate": "2022-04-16T16:14:01-04:00", "subject": "6x \"unknown\" -> \"a Promise\""}, {"hash": "57d6f4916a8008399a34e79487d3800087bbeb58", "parents": "ada1bd663058d1082815d546e63059e870a933af", "author": "Michael Dyck", "date": "2022-08-30T10:07:42-04:00", "adate": "2022-04-16T16:12:55-04:00", "subject": "6x \"unknown\" -> \"a String or ~empty~\""}, {"hash": "ada1bd663058d1082815d546e63059e870a933af", "parents": "742c4248006f0a8852edde1022b76a3e785a524b", "author": "Michael Dyck", "date": "2022-08-30T10:07:42-04:00", "adate": "2022-04-16T16:11:25-04:00", "subject": "6x \"unknown\" -> \"a TypedArray element type\""}, {"hash": "742c4248006f0a8852edde1022b76a3e785a524b", "parents": "730a15fbad9fc5a42d497335b44dbb76fd0bef8f", "author": "Michael Dyck", "date": "2022-08-30T10:07:42-04:00", "adate": "2022-04-16T16:10:03-04:00", "subject": "6x \"unknown\" -> \"an Environment Record\""}, {"hash": "730a15fbad9fc5a42d497335b44dbb76fd0bef8f", "parents": "b90e4456e3ca9c6253702023fcb62a7b7f7af6b9", "author": "Michael Dyck", "date": "2022-08-30T10:07:42-04:00", "adate": "2022-04-16T16:08:06-04:00", "subject": "7x \"unknown\" -> \"an Environment Record or *undefined*\""}, {"hash": "b90e4456e3ca9c6253702023fcb62a7b7f7af6b9", "parents": "b6d3c04e4b2752a2832082d44ff03602c9e2db52", "author": "Michael Dyck", "date": "2022-08-30T10:07:42-04:00", "adate": "2022-04-16T16:05:40-04:00", "subject": "8x \"unknown\" -> \"an Iterator Record\""}, {"hash": "b6d3c04e4b2752a2832082d44ff03602c9e2db52", "parents": "d82016b3e77a1ee5792d877d5e6c55d150dcecf3", "author": "Michael Dyck", "date": "2022-08-30T10:07:42-04:00", "adate": "2022-04-16T16:01:04-04:00", "subject": "10x \"unknown\" -> some kind of Parse Node"}, {"hash": "d82016b3e77a1ee5792d877d5e6c55d150dcecf3", "parents": "585a757938572d83e562e984f82c4253a0dab9a9", "author": "Michael Dyck", "date": "2022-08-30T10:07:42-04:00", "adate": "2022-04-16T15:58:33-04:00", "subject": "10x \"unknown\" -> \"a function object\""}, {"hash": "585a757938572d83e562e984f82c4253a0dab9a9", "parents": "8e996f9a8fefdcbda21f29fdb4f25d52abcfda63", "author": "Michael Dyck", "date": "2022-08-30T10:07:42-04:00", "adate": "2022-04-16T15:56:14-04:00", "subject": "13x \"unknown\" -> \"a String\""}, {"hash": "8e996f9a8fefdcbda21f29fdb4f25d52abcfda63", "parents": "43893644dbdf1bfa66897c9c7a1ac8b81e7f1ad2", "author": "Michael Dyck", "date": "2022-08-30T10:07:42-04:00", "adate": "2022-04-16T15:52:52-04:00", "subject": "17x \"unknown\" -> \"a List of Strings\""}, {"hash": "43893644dbdf1bfa66897c9c7a1ac8b81e7f1ad2", "parents": "0d4f0e1fae7c6dc9e5ae673cae0ce21719869da4", "author": "Michael Dyck", "date": "2022-08-30T10:07:42-04:00", "adate": "2022-04-16T15:50:30-04:00", "subject": "17x \"unknown\" -> \"an Object\""}, {"hash": "0d4f0e1fae7c6dc9e5ae673cae0ce21719869da4", "parents": "dceb9e45fa04ff37a213095e97a28da81bf213ec", "author": "Michael Dyck", "date": "2022-08-30T10:07:41-04:00", "adate": "2022-04-16T15:47:56-04:00", "subject": "75x \"unknown\" -> \"an ECMAScript language value\""}]}