{"number": 2842, "ref": "get-value", "login": "tc39", "head": "dd8eb8fe252a3097a70e45b265adeed0fa0e5de7", "base": "df65a85d02acce7a850ad811fa4b530a7cbb4f28", "title": "Editorial: GetValue and PutValue do not need to unwrap Completion Records", "created_at": "2022-08-03T21:19:42Z", "updated_at": "2022-08-03T21:26:14Z", "revs": [{"hash": "dd8eb8fe252a3097a70e45b265adeed0fa0e5de7", "parents": "5c7b1d4436d46ad4aefac4addf402439bbe31ad4", "author": "Kevin Gibbons", "date": "2022-08-03T14:25:58-07:00", "adate": "2022-08-03T14:25:58-07:00", "subject": "Editorial: GetValue and PutValue do not need to unwrap Completion Records"}, {"hash": "5c7b1d4436d46ad4aefac4addf402439bbe31ad4", "parents": "f45919c5e195b5a884e4f9f535cb88a990c4fb0c", "author": "Kevin Gibbons", "date": "2022-08-03T14:25:55-07:00", "adate": "2022-08-03T14:25:48-07:00", "subject": "Editorial: tweak ForIn/OfBodyEvaluation"}, {"hash": "f45919c5e195b5a884e4f9f535cb88a990c4fb0c", "parents": "df65a85d02acce7a850ad811fa4b530a7cbb4f28", "author": "Kevin Gibbons", "date": "2022-08-03T14:16:36-07:00", "adate": "2022-08-03T14:10:23-07:00", "subject": "Editorial: unwrap Completion Records before passing to GetValue"}]}