{"number": 1739, "ref": "function-implementation-hiding", "login": "michaelficarra", "head": "9c3c9cc8554487aa24d49c12c78e1bb976a6a6e1", "base": "7479ade585c62b4af2c66898fc0b64731f97adc6", "title": "Normative: function implementation hiding", "created_at": "2019-10-17T02:16:37Z", "updated_at": "2020-05-28T18:06:44Z", "revs": [{"hash": "9c3c9cc8554487aa24d49c12c78e1bb976a6a6e1", "parents": "49a28f827a12b1fc945e16e21891834dc762be49", "author": "Michael Ficarra", "date": "2020-05-28T11:06:32-07:00", "adate": "2020-05-27T17:12:32-07:00", "subject": "WIP stack trace censorship using the \"sensitive\" directive"}, {"hash": "49a28f827a12b1fc945e16e21891834dc762be49", "parents": "7479ade585c62b4af2c66898fc0b64731f97adc6", "author": "Michael Ficarra", "date": "2020-05-28T11:06:25-07:00", "adate": "2020-05-27T17:11:54-07:00", "subject": "function source hiding with the \"hide source\" directive"}]}