{"number": 3181, "ref": "fix-inconsistencies", "login": "linusg", "head": "15ad0cfc313b243f913b260c6129779a8e4e2323", "base": "160b260705129efbfdc54dc1570f9c5c8ef09f06", "title": "Editorial: Fix a couple of inconsistencies", "created_at": "2023-09-21T14:39:02Z", "updated_at": "2023-12-14T00:37:34Z", "revs": [{"hash": "15ad0cfc313b243f913b260c6129779a8e4e2323", "parents": "8687ede198263fec2f529e300a433be9538ef0dc", "author": "Linus Groh", "date": "2023-12-13T23:51:51+00:00", "adate": "2023-09-21T15:33:41+01:00", "subject": "Editorial: Bring {%TA%,Array}#join() and Array#toLocaleString() in sync"}, {"hash": "8687ede198263fec2f529e300a433be9538ef0dc", "parents": "cb6a2ae3e04315fa8de52414cbc0610f447222c3", "author": "Linus Groh", "date": "2023-12-13T23:46:50+00:00", "adate": "2023-09-21T15:23:19+01:00", "subject": "Editorial: Deduplicate ToString(\ud835\udd3d(k)) in Array#{indexOf,lastIndexOf}()"}, {"hash": "cb6a2ae3e04315fa8de52414cbc0610f447222c3", "parents": "c29c26ea8dfb3324b48f209e0bc4b1d0e144bcbd", "author": "Linus Groh", "date": "2023-12-13T23:46:49+00:00", "adate": "2023-09-21T15:21:04+01:00", "subject": "Editorial: Rename fromVal to fromValue in Array#{copyWithin,shift}()"}, {"hash": "c29c26ea8dfb3324b48f209e0bc4b1d0e144bcbd", "parents": "160b260705129efbfdc54dc1570f9c5c8ef09f06", "author": "Linus Groh", "date": "2023-12-13T23:46:49+00:00", "adate": "2023-09-21T15:18:53+01:00", "subject": "Editorial: Compare tv against NaN in Date.prototype.toISOString()"}]}