{"number": 1490, "ref": "anon-empty-name", "login": "anba", "head": "b3bfef067a59548ef763903a4e59ef1891508bc0", "base": "0218a39d771a76e58ffd89e5759d53004068aa2f", "title": "Set \"name\" property for anonymous functions", "created_at": "2019-03-21T20:42:11Z", "updated_at": "2020-03-02T05:05:13Z", "revs": [{"hash": "b3bfef067a59548ef763903a4e59ef1891508bc0", "parents": "36a81a0b5eb1a4aa5a3a5a59dadabdbc8717c228", "author": "Andr\u00e9 Bargull", "date": "2019-08-15T11:14:24-07:00", "adate": "2019-03-20T10:33:35-07:00", "subject": "Respecify 'anonymous function' to mean the 'name' property is the empty string instead of being absent"}, {"hash": "36a81a0b5eb1a4aa5a3a5a59dadabdbc8717c228", "parents": "6ee249e53b02f76f1a09c2d0a7e5ad3c218fb558", "author": "Andr\u00e9 Bargull", "date": "2019-08-15T11:02:25-07:00", "adate": "2019-03-20T10:33:34-07:00", "subject": "Set function name when creating a function"}, {"hash": "6ee249e53b02f76f1a09c2d0a7e5ad3c218fb558", "parents": "8f0f69279b5f9e12ebe8f7052322b93d17e36b54", "author": "Andr\u00e9 Bargull", "date": "2019-08-15T10:59:21-07:00", "adate": "2019-03-20T10:33:33-07:00", "subject": "Changed NamedEvaluation to no longer forward to normal Evaluation"}]}