{"number": 1321, "ref": "normative/extending-null", "login": "devsnek", "head": "045ebadedc76f2351e79c674640f6ec8e8c1a1f2", "base": "d03c1ec6e235a5180fa772b6178727c17974cb14", "title": "Normative: Fix extending null", "created_at": "2018-10-09T15:26:27Z", "updated_at": "2021-10-13T20:01:38Z", "revs": [{"hash": "045ebadedc76f2351e79c674640f6ec8e8c1a1f2", "parents": "d03c1ec6e235a5180fa772b6178727c17974cb14", "author": "Gus Caplan", "date": "2021-10-13T15:01:14-05:00", "adate": "2021-10-13T15:01:14-05:00", "subject": "Normative: Fix extending null"}]}