{"number": 2067, "ref": "GH-2066", "login": "tc39", "head": "67065d84df9cd112f1b0536cc2dd83904287f7d2", "base": "a4f3702259deeba04a6b22d08df92d4b88d173c8", "title": "fixes #2066: add a language tag to the document body", "created_at": "2020-06-25T18:23:58Z", "updated_at": "2020-06-29T22:57:21Z", "revs": [{"hash": "67065d84df9cd112f1b0536cc2dd83904287f7d2", "parents": "a4f3702259deeba04a6b22d08df92d4b88d173c8", "author": "Michael Ficarra", "date": "2020-06-29T15:57:15-07:00", "adate": "2020-06-25T11:22:32-07:00", "subject": "fixes #2066: add a language tag to the document (and add html/head/body)"}]}