{"number": 2848, "ref": "inclusive-range", "login": "tc39", "head": "19bd4f621f27b83e73efd92e5598c0ea45a9bb06", "base": "cd0692b082e9092a5b64aa5a8ba6ebb48161bfb2", "title": "Editorial: consistency in phrasing of ranges and inclusivity/exclusivity", "created_at": "2022-08-06T00:03:50Z", "updated_at": "2022-08-16T15:17:21Z", "revs": [{"hash": "19bd4f621f27b83e73efd92e5598c0ea45a9bb06", "parents": "f411b501e7f750408b157c49bdee0e5cca8d5f70", "author": "Michael Ficarra", "date": "2022-08-16T09:01:42-06:00", "adate": "2022-08-16T09:01:42-06:00", "subject": "be more explicit about mutual exclusion of inclusivity/exclusivity"}, {"hash": "f411b501e7f750408b157c49bdee0e5cca8d5f70", "parents": "23f7a83c02bb4cd6431c0a49107dfd26fdf0ffc0", "author": "Michael Ficarra", "date": "2022-08-16T08:59:14-06:00", "adate": "2022-08-12T11:23:53-06:00", "subject": "tweaks and examples"}, {"hash": "23f7a83c02bb4cd6431c0a49107dfd26fdf0ffc0", "parents": "ee4ef295acb4066808efba9aa1e32d3bcecd96c9", "author": "Michael Ficarra", "date": "2022-08-16T08:58:45-06:00", "adate": "2022-08-10T19:35:04-06:00", "subject": "interval bounds are no longer exclusive by default"}, {"hash": "ee4ef295acb4066808efba9aa1e32d3bcecd96c9", "parents": "2dde7545c2f8cc1e0ce42bdbd7ed69af26f7d1ea", "author": "Michael Ficarra", "date": "2022-08-16T08:58:45-06:00", "adate": "2022-08-10T19:26:18-06:00", "subject": "subvert ecmarkup lint error"}, {"hash": "2dde7545c2f8cc1e0ce42bdbd7ed69af26f7d1ea", "parents": "913b21399692507d84de217c1e9758befb27d345", "author": "Michael Ficarra", "date": "2022-08-16T08:58:45-06:00", "adate": "2022-08-10T19:19:54-06:00", "subject": "use more intervals"}, {"hash": "913b21399692507d84de217c1e9758befb27d345", "parents": "2657ac63930c0bbfc8a7f409bf74be9ac3558909", "author": "Michael Ficarra", "date": "2022-08-16T08:58:45-06:00", "adate": "2022-08-10T18:07:21-06:00", "subject": "order -0 before +0 ... I'm sorry"}, {"hash": "2657ac63930c0bbfc8a7f409bf74be9ac3558909", "parents": "cd0692b082e9092a5b64aa5a8ba6ebb48161bfb2", "author": "Michael Ficarra", "date": "2022-08-16T08:58:45-06:00", "adate": "2022-08-05T17:58:47-06:00", "subject": "Editorial: consistency in phrasing of ranges and inclusivity/exclusivity"}]}