{"number": 3249, "ref": "fixPk", "login": "zhangenming", "head": "329069469609d8f05ad64c328e2295c171050ce4", "base": "a88ef724495bf0ca3d961e26885bf382aad4320c", "title": "Editorial: use _Pk_ for unity of content and form", "created_at": "2023-12-27T02:37:27Z", "updated_at": "2024-01-25T00:55:23Z", "revs": [{"hash": "329069469609d8f05ad64c328e2295c171050ce4", "parents": "a88ef724495bf0ca3d961e26885bf382aad4320c", "author": "zhangenming", "date": "2024-01-24T16:53:18-08:00", "adate": "2024-01-24T16:53:18-08:00", "subject": "Editorial: use _Pk_ for unity of content and form (#3249)"}]}