{"number": 2232, "ref": "bump-emu", "login": "tc39", "head": "9cf4aa2aebe40ab3481de3b13367158d64ef2d05", "base": "889f2f30cf554b7ed812c0984626db1c8a4997c7", "title": "Meta: bump ecmarkup to 4.2.2", "created_at": "2020-11-23T18:30:52Z", "updated_at": "2020-11-24T04:50:15Z", "revs": [{"hash": "9cf4aa2aebe40ab3481de3b13367158d64ef2d05", "parents": "889f2f30cf554b7ed812c0984626db1c8a4997c7", "author": "Kevin Gibbons", "date": "2020-11-23T20:50:01-08:00", "adate": "2020-11-23T20:50:01-08:00", "subject": "Meta: bump ecmarkup to 4.2.2 (#2232)"}]}