{"number": 2515, "ref": "unicode-14-property-escapes", "login": "mathiasbynens", "head": "6f6c23285fa21d9d06f763111d6f89608f912e2e", "base": "a2da384e5577aa3c4e423c5f2535a44a94551376", "title": "Normative: List new Unicode v14 `Script`/`Script_Extensions` values", "created_at": "2021-09-14T12:18:42Z", "updated_at": "2021-12-23T18:13:03Z", "revs": [{"hash": "6f6c23285fa21d9d06f763111d6f89608f912e2e", "parents": "9fb13739069ceeb29415c629f3fde88df52aacb9", "author": "Kevin Gibbons", "date": "2021-12-23T10:11:36-08:00", "adate": "2021-12-23T10:10:17-08:00", "subject": "Editorial: note provenance of spellings in Script Values and General Category tables"}, {"hash": "9fb13739069ceeb29415c629f3fde88df52aacb9", "parents": "b3e6dfe61966b9a0eded9c7c5bd037b01e10abf2", "author": "Mathias Bynens", "date": "2021-09-14T14:14:22+02:00", "adate": "2021-09-14T14:14:22+02:00", "subject": "Normative: List new Unicode v14 `Script`/`Script_Extensions` values"}]}