{"number": 2777, "ref": "symbols-as-weakmap-keys", "login": "acutmore", "head": "6b9bba09a8a8471b5cb81a33c3b271940c674348", "base": "874ecf9a11ddc02a223f4250169bd2724aca0643", "title": "[Stage 4 Draft] - Symbols as WeakMap keys", "created_at": "2022-05-17T14:08:31Z", "updated_at": "2023-01-27T14:05:23Z", "revs": [{"hash": "6b9bba09a8a8471b5cb81a33c3b271940c674348", "parents": "deb935bbeb9103a4ea95a9e709b9d17c19690320", "author": "Ashley Claymore", "date": "2023-01-27T13:57:21+00:00", "adate": "2023-01-27T13:57:21+00:00", "subject": "update identity of symbols"}, {"hash": "deb935bbeb9103a4ea95a9e709b9d17c19690320", "parents": "3767ef948dbaae993689e1a9eec213259e84f342", "author": "Ashley Claymore", "date": "2023-01-27T13:56:44+00:00", "adate": "2023-01-27T13:33:12+00:00", "subject": "Apply suggestions regarding 'referent'"}, {"hash": "3767ef948dbaae993689e1a9eec213259e84f342", "parents": "ff527c67d6e0bfb5e13ac23b5267c00632812d2e", "author": "Ashley Claymore", "date": "2023-01-25T12:29:33+00:00", "adate": "2023-01-25T12:29:33+00:00", "subject": "Apply suggestions for code review"}, {"hash": "ff527c67d6e0bfb5e13ac23b5267c00632812d2e", "parents": "874ecf9a11ddc02a223f4250169bd2724aca0643", "author": "Daniel Ehrenberg", "date": "2023-01-19T15:56:34+00:00", "adate": "2020-06-09T19:31:45+02:00", "subject": "Normative: Permit Symbol as WeakMap key and WeakSet entry"}]}