{"number": 2622, "ref": "2022-01-phrasing-consistency", "login": "gibson042", "head": "f8f01032d712d101edbf5c07bc680140f2a4b30e", "base": "d9ab5c0c04d7f6edfa6c0932adccc92189e67d1a", "title": "Editorial: Use consistent phrasing for parameters that are Number or BigInt", "created_at": "2022-01-13T20:29:42Z", "updated_at": "2022-01-13T20:29:42Z", "revs": [{"hash": "f8f01032d712d101edbf5c07bc680140f2a4b30e", "parents": "d9ab5c0c04d7f6edfa6c0932adccc92189e67d1a", "author": "Richard Gibson", "date": "2022-01-13T15:26:40-05:00", "adate": "2022-01-13T15:26:40-05:00", "subject": "Editorial: Use consistent phrasing for parameters that are Number or BigInt"}]}