{"number": 2459, "ref": "DefaultConstructor", "login": "h2oche", "head": "ea2e942850a72486d9cffacae0b575441088096b", "base": "f72dd1650d62b98d008f169dced06c72aa6986d9", "title": "Editorial: Set [[Construct]] for default constructor in ClassDefiniti\u2026", "created_at": "2021-07-16T05:36:01Z", "updated_at": "2021-08-19T00:57:19Z", "revs": [{"hash": "ea2e942850a72486d9cffacae0b575441088096b", "parents": "f72dd1650d62b98d008f169dced06c72aa6986d9", "author": "h2oche", "date": "2021-08-19T09:55:58+09:00", "adate": "2021-07-16T14:13:29+09:00", "subject": "Editorial: Set [[Construct]] for default constructor in ClassDefinitionEvaluation"}]}